MANIFEST.in
README.txt
setup.cfg
setup.py
docs/HISTORY.txt
docs/INSTALL.txt
docs/LICENSE.GPL
docs/LICENSE.txt
sc/__init__.py
sc.paster.policy.egg-info/PKG-INFO
sc.paster.policy.egg-info/SOURCES.txt
sc.paster.policy.egg-info/dependency_links.txt
sc.paster.policy.egg-info/entry_points.txt
sc.paster.policy.egg-info/namespace_packages.txt
sc.paster.policy.egg-info/not-zip-safe
sc.paster.policy.egg-info/requires.txt
sc.paster.policy.egg-info/top_level.txt
sc/paster/__init__.py
sc/paster/policy/__init__.py
sc/paster/policy/portal_policy.py
sc/paster/policy/docs/sc_plone_app.txt
sc/paster/policy/templates/portal_policy/MANIFEST.in_tmpl
sc/paster/policy/templates/portal_policy/setup.cfg
sc/paster/policy/templates/portal_policy/setup.py_tmpl
sc/paster/policy/templates/portal_policy/+namespace_package+/__init__.py
sc/paster/policy/templates/portal_policy/+namespace_package+/+namespace_package2+/__init__.py
sc/paster/policy/templates/portal_policy/+namespace_package+/+namespace_package2+/+package+/README.txt_tmpl
sc/paster/policy/templates/portal_policy/+namespace_package+/+namespace_package2+/+package+/__init__.py_tmpl
sc/paster/policy/templates/portal_policy/+namespace_package+/+namespace_package2+/+package+/config.py_tmpl
sc/paster/policy/templates/portal_policy/+namespace_package+/+namespace_package2+/+package+/configure.zcml_tmpl
sc/paster/policy/templates/portal_policy/+namespace_package+/+namespace_package2+/+package+/dependencies.zcml_tmpl
sc/paster/policy/templates/portal_policy/+namespace_package+/+namespace_package2+/+package+/quickinstaller.py_tmpl
sc/paster/policy/templates/portal_policy/+namespace_package+/+namespace_package2+/+package+/setuphandlers.py_tmpl
sc/paster/policy/templates/portal_policy/+namespace_package+/+namespace_package2+/+package+/tests.py_tmpl
sc/paster/policy/templates/portal_policy/+namespace_package+/+namespace_package2+/+package+/version.txt_tmpl
sc/paster/policy/templates/portal_policy/+namespace_package+/+namespace_package2+/+package+/browser/__init__.py
sc/paster/policy/templates/portal_policy/+namespace_package+/+namespace_package2+/+package+/browser/configure.zcml_tmpl
sc/paster/policy/templates/portal_policy/+namespace_package+/+namespace_package2+/+package+/docs/__init__.py
